Metadata-Version: 2.1
Name: Test-27-11a
Version: 0.0.2
Summary: A small example package
Home-page: https://github.com/markodjukanovic90/
Author: Marko Đukanović
Author-email: Example Author <author@example.com>
Project-URL: Homepage, https://github.com/markodjukanovic90
Project-URL: Bug Tracker, https://github.com/markodjukanovic90
Classifier: Programming Language :: Python :: 3
Classifier: License :: OSI Approved :: MIT License
Classifier: Operating System :: OS Independent
Requires-Python: >=3.6
License-File: LICENSE
Requires-Dist: sympy
